README.md
setup.py
exceptiom/__init__.py
exceptiom/exceptiom.py
exceptiom/jokes_en.py
exceptiom.egg-info/PKG-INFO
exceptiom.egg-info/SOURCES.txt
exceptiom.egg-info/dependency_links.txt
exceptiom.egg-info/top_level.txt