Metadata-Version: 2.1
Name: exceptiom
Version: 1.0.0
Summary: Make python exceptions fun
Home-page: https://github.com/aqua-regia/exceptioms
Author: Syed Hassan Ashraf
Author-email: hassanashraf8888@gmail.com
License: MIT
Platform: UNKNOWN
Classifier: License :: OSI Approved :: MIT License
Classifier: Programming Language :: Python :: 3
